scrapbooking_cli-1.1.1.dist-info/licenses/LICENSE
src/scrapbook/main.py
scrapbooking_cli-1.1.1.dist-info/METADATA
scrapbooking_cli-1.1.1.dist-info/WHEEL
scrapbooking_cli-1.1.1.dist-info/entry_points.txt
scrapbooking_cli-1.1.1.dist-info/top_level.txt
scrapbooking_cli-1.1.1.dist-info/RECORD
