Metadata-Version: 2.4
Name: scrapbooking-cli
Version: 1.1.1
Summary: Logging and journaling from the terminal
Author-email: velvetSymphony <abhishek@achandrasekar.com>
Maintainer-email: velvetSymphony <abhishek@achandrasekar.com>
License:                     GNU GENERAL PUBLIC LICENSE
Project-URL: Homepage, https://github.com/velvetSymphony/scrapbook
Requires-Python: >=3.9.0
License-File: LICENSE
Dynamic: license-file
